dxlog/__about__.py
dxlog/__init__.py
dxlog/log_reader.css
dxlog/log_reader.py
dxlog-0.1.0.dist-info/METADATA
dxlog-0.1.0.dist-info/WHEEL
dxlog-0.1.0.dist-info/entry_points.txt
dxlog-0.1.0.dist-info/licenses/LICENSE.txt
dxlog-0.1.0.dist-info/RECORD
