Metadata-Version: 2.4
Name: dxlog
Version: 0.1.0
Summary: A DNAnexus log reader.
Project-URL: Documentation, https://github.com/gloriabenoit/dxlog#readme
Project-URL: Issues, https://github.com/gloriabenoit/dxlog/issues
Project-URL: Source, https://github.com/gloriabenoit/dxlog
Author-email: Gloria Benoit <gloriabenoit921@gmail.com>
License-Expression: MIT
License-File: LICENSE.txt
Classifier: Programming Language :: Python :: 3.8
Classifier: Programming Language :: Python :: 3.9
Classifier: Programming Language :: Python :: 3.10
Classifier: Programming Language :: Python :: 3.11
Classifier: Programming Language :: Python :: 3.12
Classifier: Programming Language :: Python :: 3.13
Requires-Python: >=3.8.1
Requires-Dist: dxpy>=0.388.0
Requires-Dist: textual>=3.0.1
